dm_robotics/controllers/cartesian_6d_to_joint_velocity_mapper.cpython-310-x86_64-linux-gnu.so
dm_robotics/controllers/joint_velocity_filter.cpython-310-x86_64-linux-gnu.so
dm_robotics/controllers/libosqp.so
dm_robotics/controllers/libqdldl.so
dm_robotics_controllers.libs/libmujoco-4925a9b4.so.3.3.3
dm_robotics_controllers-0.10.0.dist-info/METADATA
dm_robotics_controllers-0.10.0.dist-info/WHEEL
dm_robotics_controllers-0.10.0.dist-info/top_level.txt
dm_robotics_controllers-0.10.0.dist-info/RECORD
