Metadata-Version: 2.4
Name: dm_robotics-controllers
Version: 0.10.0
Summary: Python bindings for dm_robotics/cpp/controllers
Home-page: https://github.com/deepmind/dm_robotics/tree/main/cpp/controllers_py
Author: DeepMind
License: Apache 2.0
Classifier: Development Status :: 5 - Production/Stable
Classifier: Programming Language :: Python :: 3
Classifier: License :: OSI Approved :: Apache Software License
Classifier: Operating System :: OS Independent
Classifier: Topic :: Software Development :: Libraries
Classifier: Topic :: Scientific/Engineering
Requires-Python: >=3.9, <3.13
Dynamic: author
Dynamic: classifier
Dynamic: description
Dynamic: description-content-type
Dynamic: home-page
Dynamic: license
Dynamic: requires-python
Dynamic: summary
